<DialogueStateDefinitions>

  <DialogueStateDefinition stateName="PurpleTentacle_initial" introText="Hey, how's it going?">
    <Choice text="How did you get here?" targetState="PurpleTentacle_backstory1" />
    <Choice text="Seen any shiny keys around?" targetState="PurpleTentacle_keyChoice1" />
    <Choice text="Nevermind, I'll keep wandering around" targetState="PurpleTentacle_final" />
  </DialogueStateDefinition>

  <DialogueStateDefinition stateName="PurpleTentacle_backstory1" introText="An interdimensional quantum teleportation machine">
    <Choice text="Cool! Can I try it out?" targetState="PurpleTentacle_backstory2" />
  </DialogueStateDefinition>

  <DialogueStateDefinition stateName="PurpleTentacle_backstory2" introText="Do you know anything about quantum mechanics?">
    <Choice text="My dad taught me how to change the brakes on my car, is it similar to that?" targetState="PurpleTentacle_backstory3" />
    <Choice text="Uhh, something with quarks and spooky long distance?" targetState="PurpleTentacle_backstory3" />
  </DialogueStateDefinition>

  <DialogueStateDefinition stateName="PurpleTentacle_backstory3" introText="I don't think you're ready"/>

  <DialogueStateDefinition stateName="PurpleTentacle_keyChoice1" introText="Maybe I have, maybe I haven't...">
    <Choice text="Could I borrow it real quick to unlock the front door?" targetState="PurpleTentacle_keyChoice2" />
  </DialogueStateDefinition>

  <DialogueStateDefinition stateName="PurpleTentacle_keyChoice2" introText="Sure, why not">
    <Item name="Key" />
  </DialogueStateDefinition>

  <DialogueStateDefinition stateName="PurpleTentacle_final" introText="See ya later"/>

</DialogueStateDefinitions>
